mdxjs_py-0.1.0a2.dist-info/METADATA
mdxjs_py-0.1.0a2.dist-info/WHEEL
mdxjs_py-0.1.0a2.dist-info/licenses/LICENSE
mdxjs_py/__init__.py
mdxjs_py/mdxjs_py.abi3.so
mdxjs_py/mock.py
mdxjs_py/py.typed
mdxjs_py-0.1.0a2.dist-info/RECORD
