Metadata-Version: 2.4
Name: mdxjs-py
Version: 0.1.0a2
Classifier: Development Status :: 3 - Alpha
Classifier: Intended Audience :: Developers
Classifier: License :: OSI Approved :: MIT License
Classifier: Operating System :: POSIX :: Linux
Classifier: Programming Language :: Rust
Classifier: Programming Language :: Python :: 3
Classifier: Programming Language :: Python :: 3.8
Classifier: Programming Language :: Python :: 3.9
Classifier: Programming Language :: Python :: 3.10
Classifier: Programming Language :: Python :: 3.11
Classifier: Programming Language :: Python :: 3.12
Classifier: Programming Language :: Python :: 3.13
Classifier: Programming Language :: Python :: Implementation :: CPython
Classifier: Topic :: Software Development :: Libraries :: Python Modules
Classifier: Topic :: Text Processing :: Markup
Classifier: Typing :: Typed
License-File: LICENSE
Summary: Python bindings for mdxjs-rs - Fast MDX to JavaScript compilation via Rust
Keywords: mdx,markdown,jsx,compiler,rust,mdxjs
Home-Page: https://github.com/SamDc73/mdxjs-py
License: MIT
Requires-Python: >=3.8
Project-URL: Homepage, https://github.com/SamDc73/mdxjs-py
Project-URL: Documentation, https://github.com/SamDc73/mdxjs-py#readme
Project-URL: Repository, https://github.com/SamDc73/mdxjs-py
Project-URL: Issues, https://github.com/SamDc73/mdxjs-py/issues
Project-URL: Changelog, https://github.com/SamDc73/mdxjs-py/blob/main/CHANGELOG.md
